ppt_translator/__init__.py
ppt_translator/cli.py
ppt_translator/memory.py
ppt_translator/pipeline.py
ppt_translator/render.py
ppt_translator/review.py
ppt_translator/translation.py
ppt_translator/utils.py
ppt_translator/vision.py
ppt_translator/providers/__init__.py
ppt_translator/providers/anthropic_provider.py
ppt_translator/providers/base.py
ppt_translator/providers/deepseek.py
ppt_translator/providers/grok_provider.py
ppt_translator/providers/openai_provider.py
pptrans-1.0.0.dist-info/licenses/LICENSE
pptrans-1.0.0.dist-info/METADATA
pptrans-1.0.0.dist-info/WHEEL
pptrans-1.0.0.dist-info/entry_points.txt
pptrans-1.0.0.dist-info/top_level.txt
pptrans-1.0.0.dist-info/RECORD
