Metadata-Version: 2.4
Name: pptrans
Version: 1.0.0
Summary: Translate PowerPoint presentations using modern LLM providers with vision-based review
Author-email: Hehan Zhao <80203549+Z-MarkUs@users.noreply.github.com>
License-Expression: MIT
Keywords: powerpoint,translation,llm,ppt,pptx,multimodal
Classifier: Development Status :: 4 - Beta
Classifier: Intended Audience :: Developers
Classifier: Programming Language :: Python :: 3
Classifier: Programming Language :: Python :: 3.10
Classifier: Programming Language :: Python :: 3.11
Classifier: Programming Language :: Python :: 3.12
Classifier: Topic :: Office/Business
Classifier: Topic :: Text Processing :: Linguistic
Requires-Python: >=3.10
License-File: LICENSE
Requires-Dist: openai>=1.0.0
Requires-Dist: anthropic>=0.18.0
Requires-Dist: python-pptx>=0.6.21
Requires-Dist: python-dotenv>=1.0.0
Requires-Dist: pyyaml>=6.0
Requires-Dist: aiohttp>=3.9.0
Requires-Dist: Pillow>=10.0.0
Provides-Extra: dev
Requires-Dist: pytest>=7.0.0; extra == "dev"
Requires-Dist: black>=23.0.0; extra == "dev"
Requires-Dist: ruff>=0.1.0; extra == "dev"
Dynamic: license-file
